disable_warnings/LICENSE
disable_warnings/README.MD
disable_warnings/__init__.py
disable_warnings/requirements.txt
disable_warnings/thirdparty.json
disable_warnings-0.10.dist-info/LICENSE.rst
disable_warnings-0.10.dist-info/METADATA
disable_warnings-0.10.dist-info/WHEEL
disable_warnings-0.10.dist-info/top_level.txt
disable_warnings-0.10.dist-info/RECORD
